{
  "parent": "periodic:recipes/root",
  "criteria": {
    "has_iron": {
        "trigger": "minecraft:inventory_changed",
        "conditions": {
          "items": [
            {
              "item": "minecraft:iron_ingot"
            }
          ]
        }
      },
    "has_coal": {
      "trigger": "minecraft:inventory_changed",
      "conditions": {
        "items": [
          {
            "item": "minecraft:coal"
          }
        ]
      }
    },
    "has_the_recipe": {
      "trigger": "minecraft:recipe_unlocked",
      "conditions": {
        "recipe": "periodic:steel"
      }
    }
  },
  "requirements": [
    [
      "has_iron",
      "has_coal",
      "has_the_recipe"
    ]
  ],
  "rewards": {
    "recipes": [
      "periodic:steel"
    ]
  }
}